{"data":{"average":58,"bid":{"price1":"54","price2":"53","price3":"52","price4":"51","price5":"50","price6":"49","price7":"48","price8":"47","price9":"46","price10":"45","que_num1":"-","que_num2":"-","que_num3":"-","que_num4":"-","que_num5":"-","que_num6":"-","que_num7":"-","que_num8":"-","que_num9":"-","que_num10":"-","volume1":"563000","volume2":"656900","volume3":"1121900","volume4":"1927900","volume5":"3710500","volume6":"2365700","volume7":"317600","volume8":"678800","volume9":"665000","volume10":"695600"},"change":53,"close":54,"country":"ID","domestic":"100.00","down":"84","exchange":"IDX","fbuy":0,"fnet":0,"foreign":"0.00","frequency":32115,"fsell":0,"high":84,"id":"LAJU-W-0","lastprice":54,"low":19,"offer":{"price1":"55","price2":"56","price3":"57","price4":"58","price5":"59","price6":"60","price7":"61","price8":"62","price9":"63","price10":"64","que_num1":"-","que_num2":"-","que_num3":"-","que_num4":"-","que_num5":"-","que_num6":"-","que_num7":"-","que_num8":"-","que_num9":"-","que_num10":"-","volume1":"307300","volume2":"140700","volume3":"569600","volume4":"742200","volume5":"372800","volume6":"1866100","volume7":"473800","volume8":"167000","volume9":"308900","volume10":"477800"},"open":19,"percentage_change":5300,"previous":1,"status":"Active","symbol":"LAJU-W","symbol_2":"LAJU-W","symbol_3":"LAJU-W","tradeable":1,"unchanged":"787","up":"281","value":20752677000,"volume":356340100,"corp_action":{"active":false,"icon":"https:\/\/assets.stockbit.com\/images\/corp_action_event_icon.svg","text":"Perusahaan Memiliki Corporate Action"},"notation":[],"uma":false,"is_foreignbs_exist":false},"message":"Orderbook successfully created"}