{"data":{"average":58,"bid":{"price1":"55","price2":"54","price3":"53","price4":"52","price5":"51","price6":"50","price7":"49","price8":"48","price9":"47","price10":"46","que_num1":"-","que_num2":"-","que_num3":"-","que_num4":"-","que_num5":"-","que_num6":"-","que_num7":"-","que_num8":"-","que_num9":"-","que_num10":"-","volume1":"2065800","volume2":"1561600","volume3":"1492700","volume4":"873100","volume5":"1284200","volume6":"1648700","volume7":"439100","volume8":"945100","volume9":"741200","volume10":"397100"},"change":54,"close":55,"country":"ID","domestic":"100.00","down":"84","exchange":"IDX","fbuy":0,"fnet":0,"foreign":"0.00","frequency":36239,"fsell":0,"high":84,"id":"LAJU-W-0","lastprice":55,"low":19,"offer":{"price1":"56","price2":"57","price3":"58","price4":"59","price5":"60","price6":"61","price7":"62","price8":"63","price9":"64","price10":"65","que_num1":"-","que_num2":"-","que_num3":"-","que_num4":"-","que_num5":"-","que_num6":"-","que_num7":"-","que_num8":"-","que_num9":"-","que_num10":"-","volume1":"545700","volume2":"988400","volume3":"1114800","volume4":"558100","volume5":"882800","volume6":"1043700","volume7":"1099100","volume8":"334800","volume9":"459000","volume10":"2545900"},"open":19,"percentage_change":5400,"previous":1,"status":"Active","symbol":"LAJU-W","symbol_2":"LAJU-W","symbol_3":"LAJU-W","tradeable":1,"unchanged":"787","up":"281","value":24262752000,"volume":415827500,"corp_action":{"active":false,"icon":"https:\/\/assets.stockbit.com\/images\/corp_action_event_icon.svg","text":"Perusahaan Memiliki Corporate Action"},"notation":[],"uma":false,"is_foreignbs_exist":false},"message":"Orderbook successfully created"}