{"data":{"average":58,"bid":{"price1":"60","price2":"59","price3":"58","price4":"57","price5":"56","price6":"55","price7":"54","price8":"53","price9":"52","price10":"51","que_num1":"-","que_num2":"-","que_num3":"-","que_num4":"-","que_num5":"-","que_num6":"-","que_num7":"-","que_num8":"-","que_num9":"-","que_num10":"-","volume1":"81600","volume2":"893900","volume3":"1368700","volume4":"3359000","volume5":"296100","volume6":"432800","volume7":"939300","volume8":"1219300","volume9":"678900","volume10":"611900"},"change":59,"close":60,"country":"ID","domestic":"100.00","down":"84","exchange":"IDX","fbuy":0,"fnet":0,"foreign":"0.00","frequency":33991,"fsell":0,"high":84,"id":"LAJU-W-0","lastprice":60,"low":19,"offer":{"price1":"61","price2":"62","price3":"63","price4":"64","price5":"65","price6":"66","price7":"67","price8":"68","price9":"69","price10":"70","que_num1":"-","que_num2":"-","que_num3":"-","que_num4":"-","que_num5":"-","que_num6":"-","que_num7":"-","que_num8":"-","que_num9":"-","que_num10":"-","volume1":"1079500","volume2":"812200","volume3":"1151000","volume4":"167700","volume5":"723500","volume6":"1664000","volume7":"327000","volume8":"88200","volume9":"362000","volume10":"954900"},"open":19,"percentage_change":5900,"previous":1,"status":"Active","symbol":"LAJU-W","symbol_2":"LAJU-W","symbol_3":"LAJU-W","tradeable":1,"unchanged":"787","up":"281","value":22363169000,"volume":383213800,"corp_action":{"active":false,"icon":"https:\/\/assets.stockbit.com\/images\/corp_action_event_icon.svg","text":"Perusahaan Memiliki Corporate Action"},"notation":[],"uma":false,"is_foreignbs_exist":false},"message":"Orderbook successfully created"}